cmsis_pack_manager/__init__.py
cmsis_pack_manager/pack_manager.py
cmsis_pack_manager/cmsis_pack_manager/__init__.py
cmsis_pack_manager/cmsis_pack_manager/libcmsis_pack_manager.dylib
cmsis_pack_manager/cmsis_pack_manager/ffi.py
cmsis_pack_manager-0.6.0.dist-info/RECORD
cmsis_pack_manager-0.6.0.dist-info/WHEEL
cmsis_pack_manager-0.6.0.dist-info/entry_points.txt
cmsis_pack_manager-0.6.0.dist-info/METADATA
cmsis_pack_manager-0.6.0.dist-info/licenses/LICENSE
