Metadata-Version: 2.4
Name: cmsis-pack-manager
Version: 0.6.0
Classifier: Development Status :: 4 - Beta
Classifier: Intended Audience :: Developers
Classifier: License :: OSI Approved :: Apache Software License
Classifier: Operating System :: MacOS
Classifier: Operating System :: Microsoft :: Windows
Classifier: Operating System :: POSIX
Classifier: Operating System :: Unix
Classifier: Programming Language :: Python
Classifier: Programming Language :: Python :: 3.8
Classifier: Programming Language :: Python :: 3.9
Classifier: Programming Language :: Python :: 3.10
Classifier: Programming Language :: Python :: 3.11
Classifier: Programming Language :: Python :: 3.12
Classifier: Programming Language :: Python :: 3.13
Classifier: Topic :: Software Development
Classifier: Topic :: Software Development :: Debuggers
Classifier: Topic :: Software Development :: Embedded Systems
Classifier: Topic :: Utilities
Requires-Dist: appdirs>=1.4,<2.0
Requires-Dist: cffi
Requires-Dist: pyyaml>=6.0,<7.0
Requires-Dist: pytest>=6.0 ; extra == 'test'
Requires-Dist: hypothesis ; extra == 'test'
Requires-Dist: jinja2 ; extra == 'test'
Provides-Extra: test
License-File: LICENSE
Summary: Python manager for CMSIS-Pack index and cache with fast Rust backend
Author: Jimmy Brisson <theotherjimmy@gmail.com>, Chris Reed <flit@me.com>, Mathias Brossard <mathias.brossard@arm.com>
Author-email: Jimmy Brisson <theotherjimmy@gmail.com>, Chris Reed <flit@me.com>, Mathias Brossard <mathias.brossard@arm.com>
Maintainer-email: Mathias Brossard <mathias.brossard@arm.com>, Chris Reed <flit@me.com>
License: Apache-2.0
Requires-Python: >=3.6
Project-URL: Documentation, https://github.com/pyocd/cmsis-pack-manager/
Project-URL: Bug Tracker, https://github.com/pyocd/cmsis-pack-manager/issues
Project-URL: Discussions, https://github.com/pyocd/cmsis-pack-manager/discussions
Project-URL: Changelog, https://github.com/pyocd/cmsis-pack-manager/releases
